regext/__init__.py
regext/regext.py
regext-0.0.4.dist-info/METADATA
regext-0.0.4.dist-info/WHEEL
regext-0.0.4.dist-info/top_level.txt
regext-0.0.4.dist-info/RECORD
