Metadata-Version: 2.1
Name: regext
Version: 0.0.4
Summary: Simple regex assistant with OpenAI API and prompt engineering
Author: Sulthan Abiyyu
License: MIT
Requires-Dist: openai
Requires-Dist: python-dotenv
